[{"id":1,"title":"Cyrtandra ×scabrella C.B. Clarke (pro sp.)","author":"Adriena Klimsch","imageWidth":439,"imageHeight":871,"image":"https://picsum.photos/id/1006/439/871"},
{"id":2,"title":"Rhynchosia cytisoides (Bertol.) Wilbur","author":"Alice Klimko","imageWidth":500,"imageHeight":716,"image":"https://picsum.photos/id/1044/500/716"},
{"id":3,"title":"Zanthoxylum oahuense Hillebr.","author":"Izak Yakob","imageWidth":446,"imageHeight":726,"image":"https://picsum.photos/id/1000/446/726"},
{"id":9,"title":"Artemisia packardiae J. Grimes & Ertter","author":"Augusta Bernocchi","imageWidth":415,"imageHeight":747,"image":"https://picsum.photos/id/1063/415/747"},
{"id":10,"title":"Nymphaea ampla (Salisb.) DC. var. ampla","author":"Matthiew Hamm","imageWidth":451,"imageHeight":891,"image":"https://picsum.photos/id/1085/451/891"},
{"id":11,"title":"Hypogymnia krogiae Ohlsson","author":"Merla Mabbot","imageWidth":411,"imageHeight":899,"image":"https://picsum.photos/id/1088/411/899"},
{"id":12,"title":"Ramalina inflata (Hook. f. & Taylor) Hook. f. & Taylor ssp. inflata","author":"Lucho Dominique","imageWidth":410,"imageHeight":762,"image":"https://picsum.photos/id/1091/410/762"},
{"id":13,"title":"Lophospermum D. Don","author":"Claresta Lynagh","imageWidth":429,"imageHeight":734,"image":"https://picsum.photos/id/1025/429/734"},
{"id":14,"title":"Verbena montevidensis Spreng.","author":"Merrill Saphin","imageWidth":466,"imageHeight":763,"image":"https://picsum.photos/id/1002/466/763"},
{"id":15,"title":"Acacia victoriae Benth.","author":"Evelyn Stent","imageWidth":484,"imageHeight":875,"image":"https://picsum.photos/id/1053/484/875"},
{"id":16,"title":"Saponaria officinalis L.","author":"Marcile Kingsley","imageWidth":482,"imageHeight":774,"image":"https://picsum.photos/id/1086/482/774"},
{"id":17,"title":"Lecidea extenuata Vain.","author":"Filia Felten","imageWidth":412,"imageHeight":803,"image":"https://picsum.photos/id/1078/412/803"},
{"id":18,"title":"Crinum L.","author":"Edlin Girardeau","imageWidth":449,"imageHeight":751,"image":"https://picsum.photos/id/1079/449/751"},
{"id":19,"title":"Cyperus diffusus Vahl","author":"Tobie Jest","imageWidth":475,"imageHeight":723,"image":"https://picsum.photos/id/1024/475/723"},
{"id":20,"title":"Lesquerella humilis Rollins","author":"Mala Bendixen","imageWidth":498,"imageHeight":781,"image":"https://picsum.photos/id/1080/498/781"},
{"id":21,"title":"Eschscholzia californica Cham.","author":"Alejandrina Screen","imageWidth":424,"imageHeight":741,"image":"https://picsum.photos/id/1017/424/741"},
{"id":22,"title":"Physalis philadelphica Lam. var. immaculata Waterf.","author":"Wayne Sherrock","imageWidth":477,"imageHeight":894,"image":"https://picsum.photos/id/1042/477/894"},
{"id":23,"title":"Muhlenbergia rigida (Kunth) Trin.","author":"Vonnie Betun","imageWidth":487,"imageHeight":759,"image":"https://picsum.photos/id/1002/487/759"},
{"id":24,"title":"Heliopsis parvifolia A. Gray","author":"Peta Boulton","imageWidth":421,"imageHeight":709,"image":"https://picsum.photos/id/1012/421/709"},
{"id":25,"title":"Dioscorea L.","author":"Bunnie January","imageWidth":458,"imageHeight":732,"image":"https://picsum.photos/id/1090/458/732"},
{"id":26,"title":"Marshallia Schreb.","author":"Chryste Giacomo","imageWidth":416,"imageHeight":720,"image":"https://picsum.photos/id/1003/416/720"},
{"id":27,"title":"Pachystachys spicata (Ruiz & Pav.) Wassh.","author":"Walther Aylett","imageWidth":427,"imageHeight":766,"image":"https://picsum.photos/id/1089/427/766"},
{"id":28,"title":"Setaria setosa (Sw.) P. Beauv. var. setosa","author":"Jodie Sanper","imageWidth":404,"imageHeight":879,"image":"https://picsum.photos/id/1043/404/879"},
{"id":29,"title":"Schoenoplectus triqueter (L.) Palla","author":"Bengt Kirley","imageWidth":432,"imageHeight":797,"image":"https://picsum.photos/id/1058/432/797"},
{"id":30,"title":"Geranium solanderi Carolin","author":"Page Munro","imageWidth":446,"imageHeight":812,"image":"https://picsum.photos/id/1073/446/812"},
{"id":31,"title":"Juncus stygius L.","author":"Angel Pickerill","imageWidth":483,"imageHeight":886,"image":"https://picsum.photos/id/1099/483/886"},
{"id":32,"title":"Paederia cruddasiana Prain","author":"Garnet Jeary","imageWidth":411,"imageHeight":797,"image":"https://picsum.photos/id/1053/411/797"},
{"id":33,"title":"Portulaca halimoides L.","author":"Gibbie Manketell","imageWidth":439,"imageHeight":723,"image":"https://picsum.photos/id/1027/439/723"},
{"id":34,"title":"Carex saxatilis L.","author":"Shaylynn Tyce","imageWidth":483,"imageHeight":725,"image":"https://picsum.photos/id/1086/483/725"},
{"id":35,"title":"Oenothera wolfii (Munz) P.H. Raven, W. Dietr. & Stubbe","author":"Constancia Kerfut","imageWidth":452,"imageHeight":728,"image":"https://picsum.photos/id/1073/452/728"},
{"id":36,"title":"Parthenium alpinum (Nutt.) Torr. & A. Gray","author":"Granger Isakson","imageWidth":402,"imageHeight":880,"image":"https://picsum.photos/id/1026/402/880"},
{"id":37,"title":"Ceratophyllum muricatum Cham.","author":"Gayla Haime","imageWidth":462,"imageHeight":835,"image":"https://picsum.photos/id/1045/462/835"},
{"id":38,"title":"Robinia neomexicana A. Gray var. neomexicana","author":"Zebulon Sallarie","imageWidth":449,"imageHeight":725,"image":"https://picsum.photos/id/1038/449/725"},
{"id":39,"title":"Setaria utowanaea (Scribn. ex Millsp.) Pilg.","author":"Adolf Gyngell","imageWidth":491,"imageHeight":852,"image":"https://picsum.photos/id/1065/491/852"},
{"id":40,"title":"Chromolaena oteroi (Monachino) R.M. King & H. Rob.","author":"Linell Kenrack","imageWidth":400,"imageHeight":785,"image":"https://picsum.photos/id/1034/400/785"},
{"id":41,"title":"Brickellia oblongifolia Nutt.","author":"Ibbie Tiebe","imageWidth":480,"imageHeight":895,"image":"https://picsum.photos/id/1037/480/895"},
{"id":42,"title":"Salmea DC.","author":"Ravid Grene","imageWidth":421,"imageHeight":745,"image":"https://picsum.photos/id/1010/421/745"},
{"id":43,"title":"Bidens reptans (L.) G. Don var. reptans","author":"Piotr Eagling","imageWidth":400,"imageHeight":872,"image":"https://picsum.photos/id/1065/400/872"},
{"id":44,"title":"Lycium hassei Greene","author":"Reggie Oade","imageWidth":485,"imageHeight":848,"image":"https://picsum.photos/id/1009/485/848"},
{"id":45,"title":"Symphyotrichum laeve (L.) Á. Löve & D. Löve var. purpuratum (Nees) G.L. Nesom","author":"Kameko Givens","imageWidth":421,"imageHeight":865,"image":"https://picsum.photos/id/1059/421/865"},
{"id":46,"title":"Keckiella ternata (Torr. ex A. Gray) Straw","author":"Ransell Sangra","imageWidth":452,"imageHeight":785,"image":"https://picsum.photos/id/1050/452/785"},
{"id":47,"title":"Phacelia parryi Torr.","author":"Jenifer Lindwall","imageWidth":442,"imageHeight":719,"image":"https://picsum.photos/id/1086/442/719"},
{"id":48,"title":"Cirsium undulatum (Nutt.) Spreng. var. undulatum","author":"Carleen Northfield","imageWidth":494,"imageHeight":721,"image":"https://picsum.photos/id/1074/494/721"},
{"id":49,"title":"Nymphoides aquatica (J.F. Gmel.) Kuntze","author":"Horton Van Zon","imageWidth":441,"imageHeight":817,"image":"https://picsum.photos/id/1100/441/817"},
{"id":50,"title":"Trachyxiphium heteroicum (Cardot) W.R. Buck","author":"Godfry Linggard","imageWidth":456,"imageHeight":887,"image":"https://picsum.photos/id/1033/456/887"}]